ragford/__init__.py
ragford/main.py
ragford-0.1.5.post2.dist-info/LICENSE
ragford-0.1.5.post2.dist-info/METADATA
ragford-0.1.5.post2.dist-info/WHEEL
ragford-0.1.5.post2.dist-info/entry_points.txt
ragford-0.1.5.post2.dist-info/RECORD
